cvision/__init__.py
cvision/cvision.py
cvision-0.0.6.dist-info/LICENSE.txt
cvision-0.0.6.dist-info/METADATA
cvision-0.0.6.dist-info/WHEEL
cvision-0.0.6.dist-info/top_level.txt
cvision-0.0.6.dist-info/RECORD
