Metadata-Version: 2.1
Name: cvision
Version: 0.0.6
Summary: Computer vision package
Home-page: UNKNOWN
Author: Dr Anna Sung and Prof Kelvin Leong
Author-email: <k.leong@chester.ac.uk>
License: UNKNOWN
Keywords: python,first package
Platform: UNKNOWN
Classifier: Development Status :: 3 - Alpha
Classifier: Intended Audience :: Education
Classifier: Programming Language :: Python :: 2
Classifier: Programming Language :: Python :: 3
Classifier: Operating System :: MacOS :: MacOS X
Classifier: Operating System :: Microsoft :: Windows
License-File: LICENSE.txt
